sgtpyutils/__init__.py
sgtpyutils/__version__.py
sgtpyutils/paths.py
sgtpyutils/ExceptionHandler/__init__.py
sgtpyutils/ascii/__init__.py
sgtpyutils/binary_tree/__init__.py
sgtpyutils/binary_tree/base_tree.py
sgtpyutils/binary_tree/full_tree.py
sgtpyutils/binary_tree/full_tree_ex.py
sgtpyutils/binary_tree/node.py
sgtpyutils/binary_tree/ordered_tree.py
sgtpyutils/configuration/BaseConfiguration.py
sgtpyutils/configuration/RedisConfiguration.py
sgtpyutils/configuration/__init__.py
sgtpyutils/crypto/__init__.py
sgtpyutils/crypto/demo.py
sgtpyutils/crypto/demo_3des.py
sgtpyutils/crypto/demo_aes.py
sgtpyutils/crypto/demo_blowfish.py
sgtpyutils/crypto/demo_des.py
sgtpyutils/crypto/demo_rsa.py
sgtpyutils/crypto/utils.py
sgtpyutils/data/__init__.py
sgtpyutils/data/data_tree.py
sgtpyutils/database/__init__.py
sgtpyutils/database/BaseSaver/ISaver.py
sgtpyutils/database/BaseSaver/__init__.py
sgtpyutils/database/filebase_database/__init__.py
sgtpyutils/datetime/__init__.py
sgtpyutils/encode/__init__.py
sgtpyutils/encode/basexx/__init__.py
sgtpyutils/encode/basexx/base58.py
sgtpyutils/encode/basexx/base91.py
sgtpyutils/encode/basexx/transform_table.py
sgtpyutils/extensions/__init__.py
sgtpyutils/extensions/clazz.py
sgtpyutils/extensions/clazz_ext.py
sgtpyutils/extensions/itertools.py
sgtpyutils/extensions/typing.py
sgtpyutils/functools/__init__.py
sgtpyutils/functools/utils.py
sgtpyutils/hash/__init__.py
sgtpyutils/logger/CommonLog.py
sgtpyutils/logger/SimpleLog.py
sgtpyutils/logger/__init__.py
sgtpyutils/math/__init__.py
sgtpyutils/maze/__init__.py
sgtpyutils/network/TcpClient.py
sgtpyutils/network/__init__.py
sgtpyutils/network/SimpleCaculateService/__init__.py
sgtpyutils/network/SimpleTcpService/__init__.py
sgtpyutils/network/SimpleTcpService/BaseTcpHandler/__init__.py
sgtpyutils/network/SimpleTcpService/EventArgs/__init__.py
sgtpyutils/network/SimpleTcpService/MessageHandler/__init__.py
sgtpyutils/network/httpx/UserAgent.py
sgtpyutils/network/httpx/__init__.py
sgtpyutils-1.20.8.dist-info/METADATA
sgtpyutils-1.20.8.dist-info/WHEEL
sgtpyutils-1.20.8.dist-info/top_level.txt
sgtpyutils-1.20.8.dist-info/RECORD
