Metadata-Version: 2.4
Name: sgtpyutils
Version: 1.20.8
Summary: sgtpyutils is a public library for use.
Home-page: https://github.com/serfend/sgtpyutils
Author: serfend
Author-email: serfend@foxmail.com
License: MIT Licence
Keywords: lib,utils
Platform: any
Classifier: Development Status :: 5 - Production/Stable
Classifier: Environment :: Web Environment
Classifier: Intended Audience :: Developers
Classifier: License :: OSI Approved :: Apache Software License
Classifier: Natural Language :: English
Classifier: Operating System :: OS Independent
Classifier: Programming Language :: Python
Classifier: Programming Language :: Python :: 3
Classifier: Programming Language :: Python :: 3.7
Classifier: Programming Language :: Python :: 3.8
Classifier: Programming Language :: Python :: 3.9
Classifier: Programming Language :: Python :: 3.10
Classifier: Programming Language :: Python :: 3.11
Classifier: Programming Language :: Python :: 3 :: Only
Classifier: Programming Language :: Python :: Implementation :: CPython
Classifier: Programming Language :: Python :: Implementation :: PyPy
Classifier: Topic :: Software Development :: Libraries
Requires-Python: >=3.9, <4
Requires-Dist: scidatetime>=1.20.3
Requires-Dist: pycryptodome
Requires-Dist: colorlog
Requires-Dist: openpyxl>=3.1.0
Requires-Dist: argparse
Requires-Dist: httpx[http2]
Requires-Dist: redis
Requires-Dist: fake-useragent
Requires-Dist: six
Requires-Dist: pathlib2
Requires-Dist: typing_extensions>=4.9.0
Dynamic: author
Dynamic: author-email
Dynamic: classifier
Dynamic: description
Dynamic: description-content-type
Dynamic: home-page
Dynamic: keywords
Dynamic: license
Dynamic: platform
Dynamic: requires-dist
Dynamic: requires-python
Dynamic: summary
